{"success":true,"data":{"items":[{"id":"cmfdx1e8e0006zs302crmsh1q","name":"นายสมคิด ช่างเทคนิค","email":"technician@catcarwash.com","phone":"+66823456789","line":"@technician_th","address":"456 ถนนรัชดาภิเษก แขวงห้วยขวาง เขตห้วยขวาง กรุงเทพมหานคร 10310","status":"ACTIVE","created_at":"2025-09-10 18:48:17","updated_at":"2025-09-10 18:48:17","permission":{"id":"cmfdx1e1r0000zs30sqnjyqdc","name":"ADMIN"}},{"id":"cmfdx1e890004zs301zkzi23i","name":"นายสมพงษ์ ผู้ดูแลระบบหลัก","email":"superadmin@catcarwash.com","phone":"+66812345678","line":"@superadmin_th","address":"123 ถนนสุขุมวิท แขวงคลองตัน เขตวัฒนา กรุงเทพมหานคร 10110","status":"ACTIVE","created_at":"2025-09-10 18:48:17","updated_at":"2025-09-10 18:48:17","permission":{"id":"cmfdx1e1r0000zs30sqnjyqdc","name":"ADMIN"}}],"total":2,"page":1,"limit":5,"totalPages":1},"message":"Emps searched successfully"}